examine_files/__init__.py
examine_files/examine_files.py
examine_files-0.1.0.dist-info/AUTHORS.rst
examine_files-0.1.0.dist-info/LICENSE
examine_files-0.1.0.dist-info/METADATA
examine_files-0.1.0.dist-info/WHEEL
examine_files-0.1.0.dist-info/entry_points.txt
examine_files-0.1.0.dist-info/top_level.txt
examine_files-0.1.0.dist-info/RECORD
