Metadata-Version: 2.1
Name: examine-files
Version: 0.1.0
Summary: Checks to see if magic number contents of files match extensions. Mostly a CTF tool.
Home-page: https://github.com/hobnobpirate/examine_files
Author: hnp
Author-email: hobnobpirate@gmail.com
License: MIT license
Keywords: examine_files
Platform: UNKNOWN
Classifier: Development Status :: 2 - Pre-Alpha
Classifier: Intended Audience :: Developers
Classifier: License :: OSI Approved :: MIT License
Classifier: Natural Language :: English
Classifier: Programming Language :: Python :: 3.6
Classifier: Programming Language :: Python :: 3.7
Requires-Dist: prettytable (==0.7.2)
Requires-Dist: python-magic (==0.4.15)
